sksurgeryspherefitting/__init__.py
sksurgeryspherefitting/__main__.py
sksurgeryspherefitting/_version.py
sksurgeryspherefitting/algorithms/__init__.py
sksurgeryspherefitting/algorithms/sphere_fitting.py
sksurgeryspherefitting/ui/__init__.py
sksurgeryspherefitting/ui/sksurgeryspherefitting_command_line.py
sksurgeryspherefitting/ui/sksurgeryspherefitting_demo.py
scikit_surgery_sphere_fitting-0.0.3.dist-info/LICENSE
scikit_surgery_sphere_fitting-0.0.3.dist-info/METADATA
scikit_surgery_sphere_fitting-0.0.3.dist-info/WHEEL
scikit_surgery_sphere_fitting-0.0.3.dist-info/entry_points.txt
scikit_surgery_sphere_fitting-0.0.3.dist-info/top_level.txt
scikit_surgery_sphere_fitting-0.0.3.dist-info/RECORD
