Metadata-Version: 2.1
Name: scikit-surgery-sphere-fitting
Version: 0.0.3
Summary: scikit-surgery-sphere-fitting implements a least squares sphere fitting algorithm, to read a vtk poly data file, a config file, and outputs the fitted sphere
Home-page: https://weisslab.cs.ucl.ac.uk/StephenThompson/sksurgeryspherefitting
Author: Stephen Thompson
Author-email: s.thompson@ucl.ac.uk
License: BSD-3 license
Keywords: medical imaging
Platform: UNKNOWN
Classifier: Development Status :: 3 - Alpha
Classifier: Intended Audience :: Developers
Classifier: Intended Audience :: Healthcare Industry
Classifier: Intended Audience :: Information Technology
Classifier: Intended Audience :: Science/Research
Classifier: License :: OSI Approved :: BSD License
Classifier: Programming Language :: Python
Classifier: Programming Language :: Python :: 3
Classifier: Topic :: Scientific/Engineering :: Information Analysis
Classifier: Topic :: Scientific/Engineering :: Medical Science Apps.
Requires-Dist: numpy (>=1.11)
Requires-Dist: scipy
Requires-Dist: vtk
Requires-Dist: scikit-surgeryvtk
